QuantumIntelligence/__init__.py
QuantumIntelligence/AutomatedTheoremProving/WuMethod.py
QuantumIntelligence/AutomatedTheoremProving/__init__.py
QuantumIntelligence/BasicFunSZZ/BasicClass.py
QuantumIntelligence/BasicFunSZZ/BasicFunctions_szz.py
QuantumIntelligence/BasicFunSZZ/Geometry.py
QuantumIntelligence/BasicFunSZZ/Polynomial.py
QuantumIntelligence/BasicFunSZZ/__init__.py
QuantumIntelligence/BasicFunSZZ/physical_fun.py
QuantumIntelligence/BasicFunSZZ/tensor_trick.py
QuantumIntelligence/BasicFunSZZ/wheel_function.py
QuantumIntelligence/QuantumSimulator/Circuit.py
QuantumIntelligence/QuantumSimulator/Gate.py
QuantumIntelligence/QuantumSimulator/Simulator.py
QuantumIntelligence/QuantumSimulator/__init__.py
QuantumIntelligence/TEBD/MPSclass.py
QuantumIntelligence/TEBD/TEBD.py
QuantumIntelligence/TEBD/TNclass.py
QuantumIntelligence/TEBD/__init__.py
quantumintelligence-0.0.17.dist-info/licenses/LICENSE
quantumintelligence-0.0.17.dist-info/METADATA
quantumintelligence-0.0.17.dist-info/WHEEL
quantumintelligence-0.0.17.dist-info/top_level.txt
quantumintelligence-0.0.17.dist-info/RECORD
